singer/__init__.py
singer/bookmarks.py
singer/catalog.py
singer/exceptions.py
singer/logger.py
singer/logging.conf
singer/messages.py
singer/metadata.py
singer/metrics.py
singer/requests.py
singer/schema.py
singer/statediff.py
singer/transform.py
singer/utils.py
tests/__init__.py
tests/test_bookmarks.py
tests/test_catalog.py
tests/test_exceptions.py
tests/test_metadata.py
tests/test_metrics.py
tests/test_schema.py
tests/test_singer.py
tests/test_statediff.py
tests/test_transform.py
tests/test_utils.py
singer_python_fork-5.12.2.dist-info/LICENSE
singer_python_fork-5.12.2.dist-info/METADATA
singer_python_fork-5.12.2.dist-info/WHEEL
singer_python_fork-5.12.2.dist-info/top_level.txt
singer_python_fork-5.12.2.dist-info/RECORD
