Metadata-Version: 2.1
Name: singer-python-fork
Version: 5.12.2
Summary: Singer.io utility library
Home-page: http://singer.io
Author: Stitch
License: UNKNOWN
Platform: UNKNOWN
Classifier: Programming Language :: Python :: 3 :: Only
License-File: LICENSE
Requires-Dist: pytz (>=2018.4)
Requires-Dist: jsonschema (==3.2.0)
Requires-Dist: simplejson (==3.11.1)
Requires-Dist: python-dateutil (>=2.6.0)
Requires-Dist: backoff (==1.8.0)
Requires-Dist: ciso8601
Provides-Extra: dev
Requires-Dist: pylint ; extra == 'dev'
Requires-Dist: ipython ; extra == 'dev'
Requires-Dist: ipdb ; extra == 'dev'
Requires-Dist: nose ; extra == 'dev'
Requires-Dist: singer-tools ; extra == 'dev'
